LICENSE.rst
MANIFEST.in
README.rst
setup.py
./scikits/__init__.py
lib/colnew.f.patch
lib/colnew.pyf
lib/dgefa.f
lib/dgesl.f
lib/mus.pyf
lib/mus1.f.patch
lib/mus3.f.patch
lib/patchit.py
scikits/__init__.py
scikits.bvp1lg.egg-info/PKG-INFO
scikits.bvp1lg.egg-info/SOURCES.txt
scikits.bvp1lg.egg-info/dependency_links.txt
scikits.bvp1lg.egg-info/namespace_packages.txt
scikits.bvp1lg.egg-info/not-zip-safe
scikits.bvp1lg.egg-info/requires.txt
scikits.bvp1lg.egg-info/top_level.txt
scikits/bvp1lg/__init__.py
scikits/bvp1lg/colnew.py
scikits/bvp1lg/complex_adapter.py
scikits/bvp1lg/error.py
scikits/bvp1lg/examples.py
scikits/bvp1lg/jacobian.py
scikits/bvp1lg/mus.py
scikits/bvp1lg/setup.py
scikits/bvp1lg/version.py
scikits/bvp1lg/tests/test_colnew.py
scikits/bvp1lg/tests/test_examples.py
scikits/bvp1lg/tests/test_jacobian.py
scikits/bvp1lg/tests/test_mus.py
scikits/bvp1lg/tests/test_problems.py
scikits/bvp1lg/tests/testutils.py